{
    "dependencies": {
        "express": "registry:npm/express#4.14.0+20160925001530",
        "requirejs": "registry:npm/requirejs#2.2.0+20160319062357"
    },
    "devDependencies": {},
    "globalDependencies": {
        "bootstrap": "registry:dt/bootstrap#3.3.5+20160619023404",
        "es6-shim": "github:DefinitelyTyped/DefinitelyTyped/es6-shim/es6-shim.d.ts#4de74cb527395c13ba20b438c3a7a419ad931f1c",
        "express": "registry:dt/express#4.0.0+20160317120654",
        "express-serve-static-core": "registry:dt/express-serve-static-core#0.0.0+20160625155614",
        "jquery": "registry:dt/jquery#1.10.0+20160620094458",
        "mime": "registry:dt/mime#0.0.0+20160316155526",
        "node": "registry:dt/node#6.0.0+20161019125345",
        "require": "registry:dt/require#2.1.20+20160316155526",
        "serve-static": "registry:dt/serve-static#0.0.0+20160606155157"
    }
}
